austro/__init__.py
austro/asm/__init__.py
austro/asm/asm_lexer.py
austro/asm/assembler.py
austro/asm/memword.py
austro/shared.py
austro/simulator/__init__.py
austro/simulator/cpu.py
austro/simulator/register.py
austro/ui/__init__.py
austro/ui/codeeditor.py
austro/ui/datamodel.py
austro/ui/html/instructions.html
austro/ui/images/block-diagram.png
austro/ui/images/qt-logo.png
austro/ui/mainwindow.py
austro/ui/mainwindow.ui
austro/ui/models.py
austro/ui/qml/computer.qml
austrosim-0.1.0.dist-info/COPYING
austrosim-0.1.0.dist-info/METADATA
austrosim-0.1.0.dist-info/WHEEL
austrosim-0.1.0.dist-info/entry_points.txt
austrosim-0.1.0.dist-info/RECORD
