Metadata-Version: 2.3
Name: austrosim
Version: 0.1.0
Summary: A CPU simulator resembling Intel 8086.
License: GPL-3.0-or-later
Author: Wagner Macedo
Author-email: wagnerluis1982@gmail.com
Requires-Python: >=3.8,<4.0
Classifier: License :: OSI Approved :: GNU General Public License v3 or later (GPLv3+)
Classifier: Programming Language :: Python :: 3
Classifier: Programming Language :: Python :: 3.8
Classifier: Programming Language :: Python :: 3.9
Classifier: Programming Language :: Python :: 3.10
Classifier: Programming Language :: Python :: 3.11
Classifier: Programming Language :: Python :: 3.12
Classifier: Programming Language :: Python :: 3.13
Requires-Dist: ply (>=3.11,<4.0)
Requires-Dist: pyqt5 (>=5.15.11,<6.0.0)
